MANIFEST.in
setup.cfg
setup.py
attk/.DS_Store
attk/README.md
attk/__init__.py
attk/__init__.pyc
attk/diarize.py
attk/excerpt_class.py
attk/find_applause.py
attk/random_tag.py
attk/segment.py
attk/transcribe.py
attk/transcribe.pyc
attk/utils.py
attk/utils.pyc
attk.egg-info/PKG-INFO
attk.egg-info/SOURCES.txt
attk.egg-info/dependency_links.txt
attk.egg-info/not-zip-safe
attk.egg-info/requires.txt
attk.egg-info/top_level.txt
attk/data/knnSpeakerAll
attk/data/knnSpeakerAll.arff
attk/data/knnSpeakerFemaleMale
attk/data/knnSpeakerFemaleMale.arff
attk/data/svm_applause_model
attk/data/svm_applause_model.arff
attk/data/svm_applause_modelMEANS