Metadata-Version: 1.1
Name: attk
Version: 0.0.6
Summary: Audio Tagging Toolkit: A collection of scripts to expedite audio annotation and classifier training.
Home-page: https://github.com/hipstas/audio-tagging-toolkit
Author: Stephen Reid McLaughlin
Author-email: stephen.mclaughlin@utexas.edu
License: Apache 2.0
Keywords: audio music speech classification tagging labeling ml supervised
Platform: UNKNOWN
Classifier: Development Status :: 3 - Alpha
